scidag/__init__.py
scidag/init.py
scidag/scidag.py
scidag-0.1.0.dist-info/LICENSE
scidag-0.1.0.dist-info/METADATA
scidag-0.1.0.dist-info/WHEEL
scidag-0.1.0.dist-info/top_level.txt
scidag-0.1.0.dist-info/RECORD
