Metadata-Version: 2.1
Name: scidag
Version: 0.1.0
Summary: A simple library to manage scikit-learn DAGs
Home-page: https://github.com/detend/scidag
Author: Vahid Pourheidari
Author-email: vahid.pourheidari@gmail.com
Classifier: Programming Language :: Python :: 3
Classifier: License :: OSI Approved :: MIT License
Classifier: Operating System :: OS Independent
Requires-Python: >=3.6
License-File: LICENSE
